mvec/__init__.py
mvec/vector.py
mvec-1.0.0.dist-info/LICENSE
mvec-1.0.0.dist-info/METADATA
mvec-1.0.0.dist-info/WHEEL
mvec-1.0.0.dist-info/top_level.txt
mvec-1.0.0.dist-info/RECORD
