Metadata-Version: 2.1
Name: mvec
Version: 1.0.0
Summary: vectors of n dimensions
Home-page: https://github.com/itsmiir/nvec
Author: miir
Author-email: itsmiir@outlook.com
License: UNKNOWN
Project-URL: Bug Tracker, https://github.com/itsmiir/nvec/issues
Platform: UNKNOWN
Classifier: Programming Language :: Python :: 3
Classifier: License :: OSI Approved :: MIT License
Classifier: Operating System :: OS Independent
Requires-Python: >=3.6
License-File: LICENSE
